pansat/__init__.py
pansat/exceptions.py
pansat/file_record.py
pansat/geometry.py
pansat/metadata.py
pansat/roi.py
pansat/time.py
pansat/catalog/__init__.py
pansat/catalog/local.py
pansat/download/__init__.py
pansat/download/accounts.py
pansat/download/commandline.py
pansat/download/providers/__init__.py
pansat/download/providers/cloudnet.py
pansat/download/providers/cloudsat_dpc.py
pansat/download/providers/copernicus.py
pansat/download/providers/data_provider.py
pansat/download/providers/discrete_provider.py
pansat/download/providers/eumetsat.py
pansat/download/providers/ges_disc.py
pansat/download/providers/goes_aws.py
pansat/download/providers/himawari_aws.py
pansat/download/providers/icare.py
pansat/download/providers/iowa_state.py
pansat/download/providers/laads_daac.py
pansat/download/providers/meteo_france.py
pansat/download/providers/noaa.py
pansat/download/providers/noaa_ncei.py
pansat/download/providers/uci.py
pansat/download/providers/data/gpm_products.json
pansat/download/providers/scrapers/__init__.py
pansat/download/providers/scrapers/open_dap.py
pansat/formats/__init__.py
pansat/formats/hdf4.py
pansat/formats/hdf5.py
pansat/products/__init__.py
pansat/products/product.py
pansat/products/product_description.py
pansat/products/ground_based/__init__.py
pansat/products/ground_based/cloudnet.py
pansat/products/ground_based/mrms.py
pansat/products/ground_based/opera.py
pansat/products/ground_based/opera/__init__.py
pansat/products/ground_based/opera/maximum_reflectivity.ini
pansat/products/ground_based/opera/rainfall_rate.ini
pansat/products/reanalysis/__init__.py
pansat/products/reanalysis/era5.py
pansat/products/reanalysis/ncep.py
pansat/products/satellite/__init__.py
pansat/products/satellite/gridsat.py
pansat/products/satellite/calipso/__init__.py
pansat/products/satellite/calipso/apro5km.ini
pansat/products/satellite/calipso/clay01km.ini
pansat/products/satellite/calipso/clay333m.ini
pansat/products/satellite/cloud_sat/__init__.py
pansat-0.1.3.dist-info/LICENSE
pansat-0.1.3.dist-info/METADATA
pansat-0.1.3.dist-info/WHEEL
pansat-0.1.3.dist-info/entry_points.txt
pansat-0.1.3.dist-info/top_level.txt
pansat-0.1.3.dist-info/RECORD
