Metadata-Version: 2.1
Name: pansat
Version: 0.1.3
Summary: Download, extraction, remapping and analysis of satellite and climate data
Home-page: https://github.com/SEE-MOF/pansat
Author: Julia Kukulies, Simon Pfreundschuh, Franz Kanngießer, Hannah Imhof
License: UNKNOWN
Platform: UNKNOWN
Classifier: Programming Language :: Python :: 3
Classifier: License :: OSI Approved :: GNU Affero General Public License v3
Classifier: Operating System :: OS Independent
Requires-Python: >=3.7
Requires-Dist: cryptography>=3.1
Requires-Dist: numpy
Requires-Dist: cdsapi
Requires-Dist: requests
Requires-Dist: xarray
Requires-Dist: pyproj
Requires-Dist: appdirs
Requires-Dist: boto3
Requires-Dist: paramiko
Requires-Dist: shapely
